Workbook
Name aporte: App!$D$18
Name patrimonio: App!$D$21
Name qtd_anos: App!$D$19
Name rendimento_carteira: App!$D$13
Name salario: App!$D$12
Name sugestao_investimento: App!$D$14
Name taxa_mensal: App!$D$20

Sheet App
B11: CONFIGURAÇÕES
B12: Salário | D12: 5000
B13: Rendimento Carteira | D13: 0.0089
B14: Sugestão de Investimento | D14: =D12*30% -> 1500
B17: INVESTIMENTO MENSAL
B18: Quanto investir por mês? | D18: 500
B19: Por quantos anos? | D19: 5
B20: Taxa de rendimento mensal? | D20: 0.01079
B21: Patrimônio acumulado? | D21: =FV(taxa_mensal,qtd_anos*12,aporte*-1) -> 41888.457
B22: Dividendos mensais? | D22: =patrimonio*rendimento_carteira -> 372.80727
B25: CENÁRIOS | D25: DIVIDENDOS
A26: 2 | B26: Quantos em 2 anos? | C26: =FV($D$20,$A26*12,$D$18*-1) -> 13613.814 | D26: =C26*rendimento_carteira -> 121.16294
A27: 5 | B27: Quantos em 5 anos? | C27: =FV($D$20,$A27*12,$D$18*-1) -> 41888.457 | D27: =C27*rendimento_carteira -> 372.80727
A28: 10 | B28: Quantos em 10 anos? | C28: =FV($D$20,$A28*12,$D$18*-1) -> 121642.11 | D28: =C28*rendimento_carteira -> 1082.6147
A29: 20 | B29: Quantos em 20 anos? | C29: =FV($D$20,$A29*12,$D$18*-1) -> 562599.2 | D29: =C29*rendimento_carteira -> 5007.1329
A30: 30 | B30: Quantos em 30 anos? | C30: =FV($D$20,$A30*12,$D$18*-1) -> 2161084.8 | D30: =C30*rendimento_carteira -> 19233.655
B33: PERFIL | C33: CONSERVADOR
B34: Valor a ser investido por mês | C34: =aporte -> 500
B36: TIPO DE FII | C36: ="PERCENTUAL - "&C33 -> PERCENTUAL - CONSERVADOR | D36: VALORES
B37: Desenvolvimento | C37: =VLOOKUP($C$33&"-"&B37,App_apoio!$A:$D,4,FALSE) -> 0 | D37: =$C$34*C37 -> 0
B38: FOF's | C38: =VLOOKUP($C$33&"-"&B38,App_apoio!$A:$D,4,FALSE) -> 0.1 | D38: =$C$34*C38 -> 50
B39: Híbrido | C39: =VLOOKUP($C$33&"-"&B39,App_apoio!$A:$D,4,FALSE) -> 0.1 | D39: =$C$34*C39 -> 50
B40: Hotelaria | C40: =VLOOKUP($C$33&"-"&B40,App_apoio!$A:$D,4,FALSE) -> 0 | D40: =$C$34*C40 -> 0
B41: Papel | C41: =VLOOKUP($C$33&"-"&B41,App_apoio!$A:$D,4,FALSE) -> 0.3 | D41: =$C$34*C41 -> 150
B42: Tijolo | C42: =VLOOKUP($C$33&"-"&B42,App_apoio!$A:$D,4,FALSE) -> 0.5 | D42: =$C$34*C42 -> 250
D43: =SUM(D37:D42) -> 500

Sheet App_apoio
A1: CHAVES | B1: PERFIL | C1: TIPO DE FII | D1: % | F1: FÓRMULA
A2: =$B$2&"-"&C2 -> Conservador-Desenvolvimento | B2: Conservador | C2: Desenvolvimento | D2: 0 | F2: Moderado-Tijolo | G2: =VLOOKUP(F2,$A:$D,4,FALSE) -> 0.4
A3: =$B$2&"-"&C3 -> Conservador-FOF's | B3: Conservador | C3: FOF's | D3: 0.1
A4: =$B$2&"-"&C4 -> Conservador-Híbrido | B4: Conservador | C4: Híbrido | D4: 0.1
A5: =$B$2&"-"&C5 -> Conservador-Hotelaria | B5: Conservador | C5: Hotelaria | D5: 0
A6: =$B$2&"-"&C6 -> Conservador-Papel | B6: Conservador | C6: Papel | D6: 0.3
A7: =$B$2&"-"&C7 -> Conservador-Tijolo | B7: Conservador | C7: Tijolo | D7: 0.5
A8: =$B$8&"-"&C8 -> Moderado-Desenvolvimento | B8: Moderado | C8: Desenvolvimento | D8: 0.1
A9: =$B$8&"-"&C9 -> Moderado-FOF's | B9: Moderado | C9: FOF's | D9: 0.1
A10: =$B$8&"-"&C10 -> Moderado-Híbrido | B10: Moderado | C10: Híbrido | D10: 0.08
A11: =$B$8&"-"&C11 -> Moderado-Hotelaria | B11: Moderado | C11: Hotelaria | D11: 0.1
A12: =$B$8&"-"&C12 -> Moderado-Papel | B12: Moderado | C12: Papel | D12: 0.22
A13: =$B$8&"-"&C13 -> Moderado-Tijolo | B13: Moderado | C13: Tijolo | D13: 0.4
A14: =$B$14&"-"&C14 -> Agressivo-Desenvolvimento | B14: Agressivo | C14: Desenvolvimento | D14: 0.2
A15: =$B$14&"-"&C15 -> Agressivo-FOF's | B15: Agressivo | C15: FOF's | D15: 0.05
A16: =$B$14&"-"&C16 -> Agressivo-Híbrido | B16: Agressivo | C16: Híbrido | D16: 0.05
A17: =$B$14&"-"&C17 -> Agressivo-Hotelaria | B17: Agressivo | C17: Hotelaria | D17: 0.1
A18: =$B$14&"-"&C18 -> Agressivo-Papel | B18: Agressivo | C18: Papel | D18: 0.5
A19: =$B$14&"-"&C19 -> Agressivo-Tijolo | B19: Agressivo | C19: Tijolo | D19: 0.1
